historical_reports_s3-0.1.1.dist-info/DESCRIPTION.rst
historical_reports_s3-0.1.1.dist-info/METADATA
historical_reports_s3-0.1.1.dist-info/RECORD
historical_reports_s3-0.1.1.dist-info/WHEEL
historical_reports_s3-0.1.1.dist-info/entry_points.txt
historical_reports_s3-0.1.1.dist-info/metadata.json
historical_reports_s3-0.1.1.dist-info/top_level.txt
s3/__about__.py
s3/__init__.py
s3/cli.py
s3/config.py
s3/entrypoints.py
s3/generate.py
s3/models.py
s3/update.py
s3/util.py
s3/tests/__init__.py
s3/tests/conftest.py
s3/tests/factories.py
s3/tests/test_everything.py
