Metadata-Version: 2.0
Name: historical-reports-s3
Version: 0.1.1
Summary: Historical function for generating full dictionary of all S3 buckets and corresponding metadata.
Home-page: https://github.com/Netflix-Skunkworks/historical-reports
Author: The Historical developers
Author-email: security@netflix.com
License: UNKNOWN
Keywords: aws,account_management,s3
Platform: UNKNOWN
Requires-Dist: historical (==0.1.1)
Requires-Dist: retrying (==1.3.3)
Requires-Dist: click (==6.7)
Provides-Extra: tests
Requires-Dist: pytest (==3.1.3); extra == 'tests'
Requires-Dist: moto (==1.1.24); extra == 'tests'
Requires-Dist: coveralls (==1.1); extra == 'tests'
Requires-Dist: factory-boy (==2.9.2); extra == 'tests'
